{
"name": "TechTok's Beta Repo",
"subtitle": "TikTok clone except the target audience is tech enthusiasts",
"description": "Thank you so much for joining the beta! If released, the beta will be in apps.",
"iconURL": "https://i.imgur.com/3cp2ibH.png",
"website": "https://colecemore.github.io",
"patreonURL": "",
"tintColor": "#6156e2",
"featuredApps": [...],
"apps": [...],
"news": [
{
"title": "Welcome to TechTok!",
"identifier": "news_d3k68ulza5",
"caption": "Introducing a new feature in AltStore!",
"date": "2025-04-25T10:46",
"tintColor": "#a456e2",
"imageURL": "",
"notify": false,
"url": "https://example.com/new_feature_details",
"appID": null
}
]
}
